Metadata-Version: 2.1
Name: compressXML
Version: 0.0.1
Summary: compressXML
Home-page: https://pypi.org/project/compressXML
Author: KuoYuan Li
Author-email: funny4875@gmail.com
Keywords: compress,XML
Classifier: License :: OSI Approved :: MIT License
Classifier: Programming Language :: Python :: 3
License-File: LICENSE.txt
